cythonfastsort/README.MD
cythonfastsort/__init__.py
cythonfastsort/requirements.txt
cythonfastsort/thirdparty.json
cythonfastsort-0.10.dist-info/LICENSE.rst
cythonfastsort-0.10.dist-info/METADATA
cythonfastsort-0.10.dist-info/WHEEL
cythonfastsort-0.10.dist-info/top_level.txt
cythonfastsort-0.10.dist-info/RECORD
