Metadata-Version: 2.1
Name: cythonfastsort
Version: 0.10
Summary: C++ parallel sorting algorithms through Cython - up to 8 times faster than NumPy 
Home-page: https://github.com/hansalemaos/cythonfastsort
Author: Johannes Fischer
Author-email: aulasparticularesdealemaosp@gmail.com
License: MIT
Keywords: isin,Cython
Classifier: Development Status :: 4 - Beta
Classifier: Programming Language :: Python :: 3 :: Only
Classifier: Programming Language :: Python :: 3.10
Classifier: Topic :: Software Development :: Libraries :: Python Modules
Classifier: Topic :: Utilities
License-File: LICENSE.rst
Requires-Dist: Cython
Requires-Dist: numpy
